{"cameraMode":{"drawMode":0,"name":"Shaded","section":"Shading Mode"},"sceneLighting":false,"audioPlay":false,"sceneViewState":{"m_AlwaysRefresh":false,"showFog":true,"showSkybox":false,"showFlares":true,"showImageEffects":true,"showParticleSystems":true,"showVisualEffectGraphs":true,"m_FxEnabled":false},"in2DMode":false,"pivot":{"x":-7.561929225921631,"y":-10.159984588623047,"z":14.764542579650879},"rotation":{"x":0.2878710925579071,"y":-0.3613048195838928,"z":0.11833103746175766,"w":0.8789700269699097},"size":20.615528106689454,"orthographic":false}